calculator_package/__init__.py
calculator_package/calculator.py
calculator_package_karolina_liszewska-1.0.0.dist-info/METADATA
calculator_package_karolina_liszewska-1.0.0.dist-info/WHEEL
calculator_package_karolina_liszewska-1.0.0.dist-info/top_level.txt
calculator_package_karolina_liszewska-1.0.0.dist-info/RECORD
