Metadata-Version: 2.1
Name: calculator-package-karolina-liszewska
Version: 1.0.0
Summary: A simple calculator package for basic mathematical operations.
Home-page: https://github.com/TuringCollegeSubmissions/klisze-DWWP.1.5
Author: Karolina Liszewska
Author-email: kzliszewska@gmail.com
Classifier: Development Status :: 3 - Alpha
Classifier: Intended Audience :: Developers
Classifier: License :: OSI Approved :: MIT License
Classifier: Programming Language :: Python :: 3
Classifier: Programming Language :: Python :: 3.6
Classifier: Programming Language :: Python :: 3.7
Classifier: Programming Language :: Python :: 3.8
Classifier: Programming Language :: Python :: 3.9
